DCM/__init__.py
DCM/main.py
DCM_CMM-0.1.dist-info/LICENSE.txt
DCM_CMM-0.1.dist-info/METADATA
DCM_CMM-0.1.dist-info/WHEEL
DCM_CMM-0.1.dist-info/top_level.txt
DCM_CMM-0.1.dist-info/RECORD
